{
  "executionId": "a22e2d98-2e7f-4727-b022-f9ab01669136",
  "exitoso": true,
  "consultaOriginal": "decime los 10 articulos mas caros",
  "titulo": "Art\u00EDculos m\u00E1s caros",
  "subtitulo": "Top 10 art\u00EDculos con mayor costo",
  "resumen": "Se obtuvo un resultado din\u00E1mico de 10 fila(s) usando las vistas autorizadas del dashboard.",
  "mensaje": "",
  "notaSeguridad": "InformesIA trabaja en modo solo lectura y solo consulta las vistas autorizadas del dashboard.",
  "tipoResultado": "consulta",
  "generadoEn": "2026-04-21T16:57:42.9290052-03:00",
  "filtrosAplicados": {
    "fechaDesde": "2026-04-01T00:00:00",
    "fechaHasta": "2026-04-21T00:00:00-03:00",
    "proveedor": null,
    "articulo": null,
    "articuloCodigo": null,
    "articuloDescripcion": null,
    "rubro": null,
    "familia": null,
    "usuario": null,
    "sucursal": null,
    "deposito": null,
    "estado": null,
    "tipoComprobante": null
  },
  "fuentesAutorizadas": [
    "vw_compras_detalle_dashboard"
  ],
  "columnas": [
    {
      "key": "IDARTICULO",
      "label": "IDARTICULO",
      "format": "texto",
      "align": "left"
    },
    {
      "key": "DESCRIPCION_ARTICULO",
      "label": "DESCRIPCION ARTICULO",
      "format": "texto",
      "align": "left"
    },
    {
      "key": "COSTO",
      "label": "COSTO",
      "format": "numero",
      "align": "right"
    },
    {
      "key": "CANTIDAD",
      "label": "CANTIDAD",
      "format": "numero",
      "align": "right"
    },
    {
      "key": "TotalDashboard",
      "label": "TotalDashboard",
      "format": "numero",
      "align": "right"
    }
  ],
  "filas": [
    {
      "values": [
        "                   646126",
        "(9639) GOTAS CHOCOLATE S/A AGUILA X 5 KG",
        "93.268",
        "2",
        "186.537"
      ]
    },
    {
      "values": [
        "*",
        "ALQUILER VIVIENDA 2025",
        "56.427",
        "1",
        "56.427"
      ]
    },
    {
      "values": [
        "                     2333",
        "DULCE DE LECHE X 10K DULZAM 4441",
        "27.543",
        "11",
        "302.968"
      ]
    },
    {
      "values": [
        "                     2051",
        "CHOC. BLOCK C/ MANI 38G 20U.COFLER 5312",
        "21.714",
        "8",
        "173.710"
      ]
    },
    {
      "values": [
        "                     1944",
        "COBERTURA AGUILA SEMIAMARGA ESPECIAL X KG 3314 1170",
        "17.013",
        "10",
        "153.118"
      ]
    },
    {
      "values": [
        "                   646121",
        "LUNCHERA WILSON (65.FB005)",
        "13.090",
        "6",
        "78.540"
      ]
    },
    {
      "values": [
        "                    11671",
        "CHOC. HAMLET LECHE ALMENDRA C/MANI 21U 45G.  220",
        "12.545",
        "2",
        "21.326"
      ]
    },
    {
      "values": [
        "                    11679",
        "CHOC. HAMLET BICOLOR 21U 42G   223",
        "12.545",
        "2",
        "21.326"
      ]
    },
    {
      "values": [
        "                    11682",
        "CHOC. HAMLET BLANCO/COOKIES 21U 45G.   222",
        "12.545",
        "2",
        "21.326"
      ]
    },
    {
      "values": [
        "                      307",
        "BOMBON BON O BON 30U LECHE 11913",
        "10.133",
        "12",
        "121.592"
      ]
    }
  ],
  "grafico": null,
  "sugerenciasRelacionadas": [
    {
      "texto": "Proveedores con mayor crecimiento en el per\u00EDodo",
      "descripcion": "Compara el gasto actual contra el per\u00EDodo anterior y ordena por variaci\u00F3n.",
      "categoria": "Ranking"
    },
    {
      "texto": "Art\u00EDculos con mayor aumento",
      "descripcion": "Detecta subas de costo promedio respecto del per\u00EDodo anterior.",
      "categoria": "Variaci\u00F3n"
    },
    {
      "texto": "Rubros con m\u00E1s participaci\u00F3n",
      "descripcion": "Muestra concentraci\u00F3n del gasto por rubro en el per\u00EDodo filtrado.",
      "categoria": "Concentraci\u00F3n"
    },
    {
      "texto": "Familias que m\u00E1s crecieron",
      "descripcion": "Compara ramas familiares contra el per\u00EDodo anterior.",
      "categoria": "Comparaci\u00F3n"
    },
    {
      "texto": "Comprobantes con mayor importe",
      "descripcion": "Lista los comprobantes m\u00E1s altos del per\u00EDodo.",
      "categoria": "Top"
    }
  ],
  "sqlGenerado": "SELECT TOP (10) d.IDARTICULO, d.DESCRIPCION_ARTICULO, d.COSTO, d.CANTIDAD, d.TotalDashboard FROM vw_compras_detalle_dashboard d WHERE (@CurFechaDesde IS NULL OR d.FECHA \u003E= @CurFechaDesde) AND (@CurFechaHasta IS NULL OR d.FECHA \u003C DATEADD(day, 1, @CurFechaHasta)) AND (@CurProveedor IS NULL OR d.CUENTA = @CurProveedor) AND (@CurArticulo IS NULL) AND (@CurArticuloCodigo IS NULL) AND (@CurArticuloDescripcion IS NULL) AND (@CurRubro IS NULL) AND (@CurFamilia IS NULL) AND (@CurUsuario IS NULL) AND (@CurSucursal IS NULL) AND (@CurDeposito IS NULL) AND (@CurTipoComprobante IS NULL) ORDER BY d.COSTO DESC"
}